setup.py
access_logs/__init__.py
access_logs/admin.py
access_logs/models.py
access_logs/tasks.py
access_logs/migrations/0001_initial.py
access_logs/migrations/0002_accesslogconfiguration.py
access_logs/migrations/0003_auto_20170504_0549.py
access_logs/migrations/__init__.py
django_access_logs.egg-info/PKG-INFO
django_access_logs.egg-info/SOURCES.txt
django_access_logs.egg-info/dependency_links.txt
django_access_logs.egg-info/requires.txt
django_access_logs.egg-info/top_level.txt